[
    {"Parameter": "total", "Type": "Integer", "Description": "Total number of txs saved in database"},
    {"Parameter": "from", "Type": "Integer", "Description": "Can be either block height or index number"},
    {"Parameter": "to", "Type": "Integer", "Description": "Can be either block height or index number"},
    {"Parameter": "count_by_subaccount", "Type": "Integer", "Description": "Count entries by subaccount"},
    {"Parameter": "next", "Type": "String Array", "Description": "List of tokens to navigate to the next pages"}
]